isopro/__init__.py
isopro/adversarial_simulation/__init__.py
isopro/adversarial_simulation/adversarial_agent.py
isopro/adversarial_simulation/adversarial_environment.py
isopro/adversarial_simulation/adversarial_simulator.py
isopro/adversarial_simulation/attack_utils.py
isopro/adversarial_simulation/main.py
isopro/agents/__init__.py
isopro/agents/ai_agent.py
isopro/base/__init__.py
isopro/base/base_component.py
isopro/base/base_wrapper.py
isopro/car_simulator/__init__.py
isopro/car_simulator/car_llm_agent.py
isopro/car_simulator/car_rl_environment.py
isopro/car_simulator/car_rl_training.py
isopro/car_simulator/carviz.py
isopro/car_simulator/llm_main.py
isopro/car_simulator/main.py
isopro/conversation_simulation/__init__.py
isopro/conversation_simulation/conversation_agent.py
isopro/conversation_simulation/conversation_environment.py
isopro/conversation_simulation/conversation_simulator.py
isopro/conversation_simulation/custom_persona.py
isopro/conversation_simulation/main.py
isopro/conversation_simulation/user_personas.py
isopro/environments/__init__.py
isopro/environments/custom_environment.py
isopro/environments/llm_orchestrator.py
isopro/environments/simulation_environment.py
isopro/examples/__init__.py
isopro/orchestration_simulation/__init__.py
isopro/orchestration_simulation/agent.py
isopro/orchestration_simulation/evaluation.py
isopro/orchestration_simulation/evaluator.py
isopro/orchestration_simulation/exceptions.py
isopro/orchestration_simulation/execution_modes.py
isopro/orchestration_simulation/main.py
isopro/orchestration_simulation/orchestration_agent_example.py
isopro/orchestration_simulation/orchestration_env.py
isopro/orchestration_simulation/run_orchestration.py
isopro/orchestration_simulation/utils.py
isopro/orchestration_simulation/components/__init__.py
isopro/orchestration_simulation/components/analysis_agent.py
isopro/orchestration_simulation/components/base_component.py
isopro/orchestration_simulation/components/llama_agent.py
isopro-0.1.7.dist-info/LICENSE
isopro-0.1.7.dist-info/METADATA
isopro-0.1.7.dist-info/WHEEL
isopro-0.1.7.dist-info/top_level.txt
isopro-0.1.7.dist-info/RECORD
