Metadata-Version: 2.1
Name: isopro
Version: 0.1.7
Summary: Intelligent Simulation Orchestration for Large Language Models
Home-page: https://github.com/iso-ai/isopro
Author: Jazmia Henry
Author-email: isojaz@isoai.co
License: Apache License 2.0
Project-URL: Bug Tracker, https://github.com/iso-ai/isopro/tree/main/.github/ISSUE_TEMPLATE.md
Project-URL: Documentation, https://github.com/yourusername/isopro/wiki
Project-URL: Examples, https://github.com/iso-ai/isopro_examples/tree/main/examples
Keywords: LLM AI simulation reinforcement-learning adversarial-attacks NLP workflow-automation computer-vision
Platform: UNKNOWN
Classifier: Development Status :: 3 - Alpha
Classifier: Intended Audience :: Developers
Classifier: Intended Audience :: Science/Research
Classifier: License :: OSI Approved :: Apache Software License
Classifier: Operating System :: OS Independent
Classifier: Programming Language :: Python :: 3
Classifier: Programming Language :: Python :: 3.7
Classifier: Programming Language :: Python :: 3.8
Classifier: Programming Language :: Python :: 3.9
Classifier: Topic :: Scientific/Engineering :: Artificial Intelligence
Classifier: Topic :: Software Development :: Libraries :: Python Modules
Requires-Python: >=3.7
License-File: LICENSE
Requires-Dist: numpy (>=1.21.0)
Requires-Dist: pandas (>=1.3.0)
Requires-Dist: opencv-python (>=4.5.0)
Requires-Dist: torch (>=2.0.0)
Requires-Dist: gymnasium (>=0.29.0)
Requires-Dist: ultralytics (>=8.0.0)
Requires-Dist: pillow (>=9.0.0)
Requires-Dist: stable-baselines3 (>=2.0.0)
Requires-Dist: scikit-learn (>=1.0.0)
Requires-Dist: transformers
Requires-Dist: sentence-transformers
Requires-Dist: langchain
Requires-Dist: langchain-openai
Requires-Dist: isozero (>=0.1.0)
Requires-Dist: iso-adverse
Requires-Dist: anthropic (>=0.3.0)
Requires-Dist: openai
Requires-Dist: nltk
Requires-Dist: rouge
Requires-Dist: matplotlib (>=3.5.0)
Requires-Dist: seaborn (>=0.11.0)
Requires-Dist: tqdm (>=4.65.0)
Requires-Dist: python-dotenv (>=0.19.0)
Requires-Dist: pyyaml (>=6.0.0)
Requires-Dist: rich (>=13.0.0)
Provides-Extra: dev
Requires-Dist: pytest (>=7.0.0) ; extra == 'dev'
Requires-Dist: pytest-cov (>=4.0.0) ; extra == 'dev'
Requires-Dist: black (>=22.0.0) ; extra == 'dev'
Requires-Dist: isort (>=5.10.0) ; extra == 'dev'
Requires-Dist: flake8 (>=4.0.0) ; extra == 'dev'
